{
    "sourceFile": "src/features/visualizer/components/DemoShowcase/index.js",
    "activeCommit": 0,
    "commits": [
        {
            "activePatchIndex": 9,
            "patches": [
                {
                    "date": 1762148258448,
                    "content": "Index: \n===================================================================\n--- \n+++ \n"
                },
                {
                    "date": 1762149763116,
                    "content": "Index: \n===================================================================\n--- \n+++ \n@@ -2,4 +2,5 @@\n export { default as CommitDemo } from \"./CommitDemo\";\r\n export { default as BranchingDemo } from \"./BranchingDemo\";\r\n export { default as MergeDemo } from \"./MergeDemo\";\r\n export { default as TestSequenceDemo } from \"./TestSequenceDemo\";\r\n+export { default as TerminalDemo } from \"./TerminalDemo\";\r\n"
                },
                {
                    "date": 1762255305054,
                    "content": "Index: \n===================================================================\n--- \n+++ \n@@ -1,6 +1,14 @@\n export { default as DemoShowcase } from \"./DemoShowcase\";\r\n+\r\n+// Old live demos (kept for reference)\r\n export { default as CommitDemo } from \"./CommitDemo\";\r\n export { default as BranchingDemo } from \"./BranchingDemo\";\r\n export { default as MergeDemo } from \"./MergeDemo\";\r\n export { default as TestSequenceDemo } from \"./TestSequenceDemo\";\r\n export { default as TerminalDemo } from \"./TerminalDemo\";\r\n+\r\n+// New static demos (lightweight, no computation)\r\n+export { default as StaticCommitDemo } from \"./StaticCommitDemo\";\r\n+export { default as StaticBranchingDemo } from \"./StaticBranchingDemo\";\r\n+export { default as StaticMergeDemo } from \"./StaticMergeDemo\";\r\n+export { default as StaticTestSequenceDemo } from \"./StaticTestSequenceDemo\";\r\n"
                },
                {
                    "date": 1762255462585,
                    "content": "Index: \n===================================================================\n--- \n+++ \n@@ -1,12 +1,12 @@\n export { default as DemoShowcase } from \"./DemoShowcase\";\r\n \r\n // Old live demos (kept for reference)\r\n-export { default as CommitDemo } from \"./CommitDemo\";\r\n-export { default as BranchingDemo } from \"./BranchingDemo\";\r\n-export { default as MergeDemo } from \"./MergeDemo\";\r\n-export { default as TestSequenceDemo } from \"./TestSequenceDemo\";\r\n-export { default as TerminalDemo } from \"./TerminalDemo\";\r\n+// export { default as CommitDemo } from \"./CommitDemo\";\r\n+// export { default as BranchingDemo } from \"./BranchingDemo\";\r\n+// export { default as MergeDemo } from \"./MergeDemo\";\r\n+// export { default as TestSequenceDemo } from \"./TestSequenceDemo\";\r\n+// export { default as TerminalDemo } from \"./TerminalDemo\";\r\n \r\n // New static demos (lightweight, no computation)\r\n export { default as StaticCommitDemo } from \"./StaticCommitDemo\";\r\n export { default as StaticBranchingDemo } from \"./StaticBranchingDemo\";\r\n"
                },
                {
                    "date": 1762255604673,
                    "content": "Index: \n===================================================================\n--- \n+++ \n@@ -0,0 +1,14 @@\n+export { default as DemoShowcase } from \"./DemoShowcase\";\r\n+\r\n+// Old live demos (kept for reference)\r\n+export { default as CommitDemo } from \"./CommitDemo\";\r\n+export { default as BranchingDemo } from \"./BranchingDemo\";\r\n+export { default as MergeDemo } from \"./MergeDemo\";\r\n+export { default as TestSequenceDemo } from \"./TestSequenceDemo\";\r\n+export { default as TerminalDemo } from \"./TerminalDemo\";\r\n+\r\n+// New static demos (lightweight, no computation)\r\n+export { default as StaticCommitDemo } from \"./StaticCommitDemo\";\r\n+export { default as StaticBranchingDemo } from \"./StaticBranchingDemo\";\r\n+export { default as StaticMergeDemo } from \"./StaticMergeDemo\";\r\n+export { default as StaticTestSequenceDemo } from \"./StaticTestSequenceDemo\";\r\n"
                },
                {
                    "date": 1762255613672,
                    "content": "Index: \n===================================================================\n--- \n+++ \n@@ -1,21 +1,7 @@\n export { default as DemoShowcase } from \"./DemoShowcase\";\r\n \r\n // Old live demos (kept for reference)\r\n-export { default as CommitDemo } from \"./CommitDemo\";\r\n-export { default as BranchingDemo } from \"./BranchingDemo\";\r\n-export { default as MergeDemo } from \"./MergeDemo\";\r\n-export { default as TestSequenceDemo } from \"./TestSequenceDemo\";\r\n-export { default as TerminalDemo } from \"./TerminalDemo\";\r\n-\r\n-// New static demos (lightweight, no computation)\r\n-export { default as StaticCommitDemo } from \"./StaticCommitDemo\";\r\n-export { default as StaticBranchingDemo } from \"./StaticBranchingDemo\";\r\n-export { default as StaticMergeDemo } from \"./StaticMergeDemo\";\r\n-export { default as StaticTestSequenceDemo } from \"./StaticTestSequenceDemo\";\r\n-export { default as DemoShowcase } from \"./DemoShowcase\";\r\n-\r\n-// Old live demos (kept for reference)\r\n // export { default as CommitDemo } from \"./CommitDemo\";\r\n // export { default as BranchingDemo } from \"./BranchingDemo\";\r\n // export { default as MergeDemo } from \"./MergeDemo\";\r\n // export { default as TestSequenceDemo } from \"./TestSequenceDemo\";\r\n"
                },
                {
                    "date": 1762255650586,
                    "content": "Index: \n===================================================================\n--- \n+++ \n@@ -1,13 +1,6 @@\n export { default as DemoShowcase } from \"./DemoShowcase\";\r\n \r\n-// Old live demos (kept for reference)\r\n-// export { default as CommitDemo } from \"./CommitDemo\";\r\n-// export { default as BranchingDemo } from \"./BranchingDemo\";\r\n-// export { default as MergeDemo } from \"./MergeDemo\";\r\n-// export { default as TestSequenceDemo } from \"./TestSequenceDemo\";\r\n-// export { default as TerminalDemo } from \"./TerminalDemo\";\r\n-\r\n // New static demos (lightweight, no computation)\r\n export { default as StaticCommitDemo } from \"./StaticCommitDemo\";\r\n export { default as StaticBranchingDemo } from \"./StaticBranchingDemo\";\r\n export { default as StaticMergeDemo } from \"./StaticMergeDemo\";\r\n"
                },
                {
                    "date": 1762255775281,
                    "content": "Index: \n===================================================================\n--- \n+++ \n@@ -1,6 +1,13 @@\n export { default as DemoShowcase } from \"./DemoShowcase\";\r\n \r\n+// Old live demos (kept for reference)\r\n+export { default as CommitDemo } from \"./CommitDemo\";\r\n+export { default as BranchingDemo } from \"./BranchingDemo\";\r\n+export { default as MergeDemo } from \"./MergeDemo\";\r\n+export { default as TestSequenceDemo } from \"./TestSequenceDemo\";\r\n+export { default as TerminalDemo } from \"./TerminalDemo\";\r\n+\r\n // New static demos (lightweight, no computation)\r\n export { default as StaticCommitDemo } from \"./StaticCommitDemo\";\r\n export { default as StaticBranchingDemo } from \"./StaticBranchingDemo\";\r\n export { default as StaticMergeDemo } from \"./StaticMergeDemo\";\r\n"
                },
                {
                    "date": 1762255784526,
                    "content": "Index: \n===================================================================\n--- \n+++ \n@@ -1,12 +1,12 @@\n export { default as DemoShowcase } from \"./DemoShowcase\";\r\n \r\n // Old live demos (kept for reference)\r\n-export { default as CommitDemo } from \"./CommitDemo\";\r\n-export { default as BranchingDemo } from \"./BranchingDemo\";\r\n-export { default as MergeDemo } from \"./MergeDemo\";\r\n-export { default as TestSequenceDemo } from \"./TestSequenceDemo\";\r\n-export { default as TerminalDemo } from \"./TerminalDemo\";\r\n+// export { default as CommitDemo } from \"./CommitDemo\";\r\n+// export { default as BranchingDemo } from \"./BranchingDemo\";\r\n+// export { default as MergeDemo } from \"./MergeDemo\";\r\n+// export { default as TestSequenceDemo } from \"./TestSequenceDemo\";\r\n+// export { default as TerminalDemo } from \"./TerminalDemo\";\r\n \r\n // New static demos (lightweight, no computation)\r\n export { default as StaticCommitDemo } from \"./StaticCommitDemo\";\r\n export { default as StaticBranchingDemo } from \"./StaticBranchingDemo\";\r\n"
                },
                {
                    "date": 1762335816259,
                    "content": "Index: \n===================================================================\n--- \n+++ \n@@ -1,12 +1,12 @@\n export { default as DemoShowcase } from \"./DemoShowcase\";\r\n \r\n // Old live demos (kept for reference)\r\n-// export { default as CommitDemo } from \"./CommitDemo\";\r\n-// export { default as BranchingDemo } from \"./BranchingDemo\";\r\n-// export { default as MergeDemo } from \"./MergeDemo\";\r\n-// export { default as TestSequenceDemo } from \"./TestSequenceDemo\";\r\n-// export { default as TerminalDemo } from \"./TerminalDemo\";\r\n+export { default as CommitDemo } from \"./CommitDemo\";\r\n+export { default as BranchingDemo } from \"./BranchingDemo\";\r\n+export { default as MergeDemo } from \"./MergeDemo\";\r\n+export { default as TestSequenceDemo } from \"./TestSequenceDemo\";\r\n+export { default as TerminalDemo } from \"./TerminalDemo\";\r\n \r\n // New static demos (lightweight, no computation)\r\n export { default as StaticCommitDemo } from \"./StaticCommitDemo\";\r\n export { default as StaticBranchingDemo } from \"./StaticBranchingDemo\";\r\n"
                }
            ],
            "date": 1762148258448,
            "name": "Commit-0",
            "content": "export { default as DemoShowcase } from \"./DemoShowcase\";\r\nexport { default as CommitDemo } from \"./CommitDemo\";\r\nexport { default as BranchingDemo } from \"./BranchingDemo\";\r\nexport { default as MergeDemo } from \"./MergeDemo\";\r\nexport { default as TestSequenceDemo } from \"./TestSequenceDemo\";\r\n"
        }
    ]
}